caselockerapi/__init__.py
caselockerapi/auth.py
caselockerapi/client.py
caselockerapi/utils.py
caselockerapi-0.9.0.dist-info/COPYING
caselockerapi-0.9.0.dist-info/COPYING.LESSER
caselockerapi-0.9.0.dist-info/LICENSE
caselockerapi-0.9.0.dist-info/METADATA
caselockerapi-0.9.0.dist-info/WHEEL
caselockerapi-0.9.0.dist-info/top_level.txt
caselockerapi-0.9.0.dist-info/RECORD
